{
  "page_number": 23,
  "tasks": [
    {
      "page_number": 23,
      "task_number": "4",
      "task_text": "Сосчитай сколько 4 на рисунке",
      "has_image": false,
      "confidence_score": 0.96,
      "processing_time": null,
      "extraction_metadata": {
        "extraction_source": "vision_api",
        "raw_task_number": "4",
        "text_cleaned": false,
        "api_task_type": "counting",
        "api_page_section": "top",
        "api_difficulty": "medium"
      },
      "created_at": "2025-07-31T14:13:50.331191"
    },
    {
      "page_number": 23,
      "task_number": "5",
      "task_text": "Сколько 1 ты видишь?",
      "has_image": false,
      "confidence_score": 0.89,
      "processing_time": null,
      "extraction_metadata": {
        "extraction_source": "vision_api",
        "raw_task_number": "5",
        "text_cleaned": false,
        "api_task_type": "counting",
        "api_page_section": "bottom",
        "api_difficulty": "hard"
      },
      "created_at": "2025-07-31T14:13:50.331870"
    }
  ],
  "processing_time": 1.785494327545166,
  "image_info": {
    "size_bytes": 2567439,
    "format": "PNG",
    "page_number": 23
  },
  "api_method": "mock",
  "task_count": 2,
  "processed_at": "2025-07-31T14:13:50.334405",
  "storage_version": "2.0"
}